guy.py
guy-0.7.5.dist-info/LICENSE
guy-0.7.5.dist-info/WHEEL
guy-0.7.5.dist-info/METADATA
guy-0.7.5.dist-info/RECORD
