Metadata-Version: 2.1
Name: guy
Version: 0.7.5
Summary: A simple module for making HTML GUI applications with python3
Home-page: https://github.com/manatlan/guy
License: Apache-2.0
Keywords: gui,html,javascript,electron,asyncio,tornado,websocket
Author: manatlan
Author-email: manatlan@gmail.com
Requires-Python: >=3.5,<4.0
Classifier: License :: OSI Approved :: Apache Software License
Classifier: Operating System :: OS Independent
Classifier: Programming Language :: Python :: 3
Classifier: Programming Language :: Python :: 3.5
Classifier: Programming Language :: Python :: 3.6
Classifier: Programming Language :: Python :: 3.7
Classifier: Programming Language :: Python :: 3.8
Classifier: Topic :: Software Development :: Build Tools
Classifier: Topic :: Software Development :: Libraries :: Python Modules
Requires-Dist: tornado (>=6.0,<7.0)
Project-URL: Documentation, https://github.com/manatlan/guy
Project-URL: Repository, https://github.com/manatlan/guy
